carehome/__init__.py
carehome/databases.py
carehome/exc.py
carehome/methods.py
carehome/objects.py
carehome/properties.py
carehome/property_types.py
carehome-4.1.1.dist-info/AUTHORS
carehome-4.1.1.dist-info/LICENSE
carehome-4.1.1.dist-info/METADATA
carehome-4.1.1.dist-info/WHEEL
carehome-4.1.1.dist-info/pbr.json
carehome-4.1.1.dist-info/top_level.txt
carehome-4.1.1.dist-info/RECORD
