Metadata-Version: 2.1
Name: carehome
Version: 4.1.1
Summary: Make objects with multiple inheritance with Python.
Home-page: https://github.com/chrisnorman7/
Author: Chris Norman
Author-email: chris.norman2@googlemail.com
License: MPL-2
Platform: UNKNOWN
Requires-Dist: attrs
